fgts_pdf_dados/__init__.py
fgts_pdf_dados/__main__.py
fgts_pdf_dados-1.2.dist-info/METADATA
fgts_pdf_dados-1.2.dist-info/WHEEL
fgts_pdf_dados-1.2.dist-info/entry_points.txt
fgts_pdf_dados-1.2.dist-info/top_level.txt
fgts_pdf_dados-1.2.dist-info/RECORD
