Metadata-Version: 2.4
Name: fgts_pdf_dados
Version: 1.2
Summary: Extrai dados de múltiplos extratos PDF da app do FGTS e grava tudo como uma série histórica num CSV pronto para usar com o Inverstorzilla
Author-email: Avi Alkalay <avi@unix.sh>
Project-URL: Homepage, https://github.com/avibrazil/fgts-pdf-dados
Project-URL: Source, https://github.com/avibrazil/fgts-pdf-dados
Project-URL: Issues, https://github.com/avibrazil/fgts-pdf-dados/issues/new/choose
Project-URL: Pypi, https://pypi.org/project/fgts-pdf-dados/
Keywords: FGTS,personal finance,Brazil
Classifier: Intended Audience :: Developers
Classifier: Programming Language :: Python :: 3
Classifier: Operating System :: OS Independent
Classifier: License :: OSI Approved :: GNU Library or Lesser General Public License (LGPL)
Classifier: Development Status :: 5 - Production/Stable
Classifier: Intended Audience :: Science/Research
Classifier: Topic :: Scientific/Engineering :: Information Analysis
Classifier: Topic :: Office/Business :: Financial :: Investment
Requires-Python: >=3.8
Requires-Dist: pandas
Requires-Dist: pdfplumber
